hw/trng/health/adaptive_prop_test.sv
`timescale 1 ns / 1 ps

// Adaptive Proportion Test (APT)
// Integration:
//   bit_in / bit_valid come from the Von Neumann / post-processing stage.
//   alarm is a level signal — stays asserted until alarm_clear from trng_ctrl.
//   keccak_enable should be gated with ~alarm externally in trng_top.

module adaptive_prop_test (
    input  logic clk,
    input  logic rst_n,

    input  logic bit_in,
    input  logic bit_valid,

    input  logic alarm_clear,

    // To trng_ctrl / oht_gate
    output logic prop_pass,
    output logic alarm
);
    localparam int unsigned W      = 512;
    localparam int unsigned C      = 410;
    localparam int unsigned W_BITS = $clog2(W + 1);
    localparam int unsigned B_BITS = $clog2(C + 1);

    // NIST SP (S → anchor, B → match_count).
    logic              S;  // first bit of the current window (NIST: S)
    logic [B_BITS-1:0] B; // number of bits matching anchor   (NIST: B)
    logic [W_BITS-1:0] pos;
    logic              first_bit;

    logic alarm_lat;
    logic alarm_comb;

    assign alarm_comb = (B >= C[B_BITS-1:0]);

    always_ff @(posedge clk or negedge rst_n) begin
        if (!rst_n)
            alarm_lat <= 1'b0;
        else if (alarm_clear)
            alarm_lat <= 1'b0;
        else if (alarm_comb)
            alarm_lat <= 1'b1;
    end

    assign alarm     = alarm_lat | alarm_comb;
    assign prop_pass = ~alarm;
    always_ff @(posedge clk or negedge rst_n) begin
        if (!rst_n) begin
            S         <= 1'b0;
            B         <= '0;
            pos       <= '0;
            first_bit <= 1'b1;
        end

        else if (alarm_clear) begin
            S         <= 1'b0;
            B         <= '0;
            pos       <= '0;
            first_bit <= 1'b1;
        end

        else if (bit_valid && !alarm_lat) begin

            if (first_bit) begin
                S         <= bit_in;
                B         <= {{(B_BITS-1){1'b0}}, 1'b1};  // B = 1
                pos       <= {{(W_BITS-1){1'b0}}, 1'b1};  // pos = 1
                first_bit <= 1'b0;

            end else begin
                if (bit_in == S)
                    B <= B + 1'b1;

                pos <= pos + 1'b1;

                if (pos == W_BITS'(W)) begin
                    first_bit <= 1'b1;
                    B         <= '0;
                    pos       <= '0;
                end
            end
        end
    end

endmodule

hw/trng/health/tb_adaptive_prop_test.sv
`timescale 1 ns / 1 ps

// Testbench: adaptive_prop_test
//
// Covers 7 scenarios:
//   TC1  Perfect alternating stream         → no alarm
//   TC2  Pseudo-random stream (LFSR)        → no alarm
//   TC3  Stuck-at-0, anchor = 0            → alarm at bit 410
//   TC4  Stuck-at-1, anchor = 1            → alarm at bit 410
//   TC5  Stuck-at-0, anchor = 1            → NO alarm (APT blind spot, by design)
//   TC6  Window boundary — clean then new  → alarm-free, first_bit resets
//   TC7  alarm_clear restores operation    → alarm, clear, then pass again

module tb_adaptive_prop_test;
    logic clk, rst_n;
    logic bit_in, bit_valid, alarm_clear;
    logic prop_pass, alarm;

    adaptive_prop_test dut (
        .clk, .rst_n,
        .bit_in, .bit_valid, .alarm_clear,
        .prop_pass, .alarm
    );

    initial clk = 0;
    always #10 clk = ~clk;

    logic [15:0] lfsr;
    function automatic logic lfsr_next_bit(input logic [15:0] state);
        return state[15] ^ state[14] ^ state[12] ^ state[3];
    endfunction

    int tc_pass_count = 0;
    int tc_fail_count = 0;

    task automatic reset_dut();
        rst_n       = 0;
        bit_valid   = 0;
        bit_in      = 0;
        alarm_clear = 0;
        repeat(4) @(posedge clk);
        #1 rst_n = 1;
        @(posedge clk);
    endtask

    task automatic send_bit(input logic b);
        @(negedge clk);
        bit_in    = b;
        bit_valid = 1;
        @(posedge clk);
        #1;
        bit_valid = 0;
    endtask

    task automatic send_const(input logic b, input int n);
        for (int i = 0; i < n; i++)
            send_bit(b);
    endtask

    task automatic send_alternating(input logic b, input int n);
        logic cur = b;
        for (int i = 0; i < n; i++) begin
            send_bit(cur);
            cur = ~cur;
        end
    endtask

    task automatic send_lfsr(input int n);
        for (int i = 0; i < n; i++) begin
            send_bit(lfsr[0]);
            lfsr = {lfsr_next_bit(lfsr), lfsr[15:1]};
        end
    endtask

    task automatic check(
        input string  label,
        input logic   got_alarm,
        input logic   expect_alarm
    );
        if (got_alarm === expect_alarm) begin
            $display("  PASS  %s  (alarm=%0b)", label, got_alarm);
            tc_pass_count++;
        end else begin
            $display("  FAIL  %s  got alarm=%0b expected=%0b",
                     label, got_alarm, expect_alarm);
            tc_fail_count++;
        end
    endtask

    initial begin
        $dumpfile("tb_adaptive_prop_test.vcd");
        $dumpvars(0, tb_adaptive_prop_test);

        $display("─────────────────────────────────────────────────────────");
        $display(" Adaptive Proportion Test — Testbench");
        $display("─────────────────────────────────────────────────────────");

        $display("\nTC1: Perfect alternating stream (512 bits) → expect no alarm");
        reset_dut();
        send_alternating(1'b0, 512);
        @(posedge clk); #1;
        check("TC1 no alarm after alternating 512b", alarm, 1'b0);

        $display("\nTC2: LFSR pseudo-random stream (1024 bits) → expect no alarm");
        reset_dut();
        lfsr = 16'hACE1;
        send_lfsr(1024);
        @(posedge clk); #1;
        check("TC2 no alarm after LFSR 1024b", alarm, 1'b0);

        $display("\nTC3: Stuck-at-0, anchor=0 → alarm must fire by bit 410");
        reset_dut();
        begin
            int alarm_cycle = -1;
            for (int i = 1; i <= 512; i++) begin
                send_bit(1'b0);
                if (alarm && alarm_cycle < 0)
                    alarm_cycle = i;
            end
            if (alarm_cycle > 0)
                $display("  INFO  alarm fired at bit %0d (expect ≤410)", alarm_cycle);
            check("TC3 alarm fires (stuck-at-0, anchor=0)", alarm, 1'b1);
            if (alarm_cycle > 410)
                $display("  WARN  alarm fired LATE at bit %0d — check C", alarm_cycle);
        end

        $display("\nTC4: Stuck-at-1, anchor=1 → alarm must fire by bit 410");
        reset_dut();
        begin
            int alarm_cycle = -1;
            for (int i = 1; i <= 512; i++) begin
                send_bit(1'b1);
                if (alarm && alarm_cycle < 0)
                    alarm_cycle = i;
            end
            if (alarm_cycle > 0)
                $display("  INFO  alarm fired at bit %0d (expect ≤410)", alarm_cycle);
            check("TC4 alarm fires (stuck-at-1, anchor=1)", alarm, 1'b1);
        end

        $display("\nTC5: Stuck-at-0, anchor=1 → expect NO alarm (APT blind spot)");
        reset_dut();
        send_bit(1'b1);
        send_const(1'b0, 511);
        @(posedge clk); #1;
        check("TC5 no alarm (blind spot, monobit/rep_count cover)", alarm, 1'b0);

        $display("\nTC6: Two back-to-back clean windows (1024 bits) → no alarm");
        reset_dut();
        send_alternating(1'b0, 512);   // window 1
        send_alternating(1'b1, 512);   // window 2
        @(posedge clk); #1;
        check("TC6 no alarm across window boundary", alarm, 1'b0);

        $display("\nTC7: alarm fires, alarm_clear asserted, then clean window passes");
        reset_dut();
        // Trigger alarm
        send_const(1'b0, 512);
        @(posedge clk); #1;
        check("TC7a alarm fires before clear", alarm, 1'b1);

        @(negedge clk);
        alarm_clear = 1;
        @(posedge clk); #1;
        alarm_clear = 0;
        @(posedge clk); #1;
        check("TC7b alarm deasserted after clear", alarm, 1'b0);
        check("TC7c prop_pass restored after clear", prop_pass, 1'b1);

        send_alternating(1'b0, 512);
        @(posedge clk); #1;
        check("TC7d no alarm after clean window post-clear", alarm, 1'b0);

        $display("\n─────────────────────────────────────────────────────────");
        $display(" Results: %0d PASS, %0d FAIL", tc_pass_count, tc_fail_count);
        $display("─────────────────────────────────────────────────────────");

        if (tc_fail_count == 0)
            $display(" ALL TESTS PASSED");
        else
            $display(" FAILURES DETECTED — review waveform: tb_adaptive_prop_test.vcd");

        $finish;
    end

    initial begin
        #5_000_000;
        $display("TIMEOUT — simulation took too long");
        $finish;
    end

endmodule

hw/trng/health/tb_adaptive_prop_test.vcd
$date
	Sun Jul  5 06:21:58 2026
$end
$version
	Icarus Verilog
$end
$timescale
	1ps
$end
$scope module tb_adaptive_prop_test $end
$var wire 1 ! prop_pass $end
$var wire 1 " alarm $end
$var reg 1 # alarm_clear $end
$var reg 1 $ bit_in $end
$var reg 1 % bit_valid $end
$var reg 1 & clk $end
$var reg 16 ' lfsr [15:0] $end
$var reg 1 ( rst_n $end
$var integer 32 ) tc_fail_count [31:0] $end
$var integer 32 * tc_pass_count [31:0] $end
$scope function lfsr_next_bit $end
$upscope $end
$scope module dut $end
$var wire 1 " alarm $end
$var wire 1 # alarm_clear $end
$var wire 1 $ bit_in $end
$var wire 1 % bit_valid $end
$var wire 1 & clk $end
$var wire 1 ! prop_pass $end
$var wire 1 ( rst_n $end
$var wire 1 + alarm_comb $end
$var parameter 32 , B_BITS $end
$var parameter 32 - C $end
$var parameter 32 . W $end
$var parameter 32 / W_BITS $end
$var reg 9 0 B [8:0] $end
$var reg 1 1 S $end
$var reg 1 2 alarm_lat $end
$var reg 1 3 first_bit $end
$var reg 10 4 pos [9:0] $end
$upscope $end
$scope begin $unm_blk_14 $end
$var integer 32 5 alarm_cycle [31:0] $end
$scope begin $ivl_for_loop3 $end
$var integer 32 6 i [31:0] $end
$upscope $end
$upscope $end
$scope begin $unm_blk_16 $end
$var integer 32 7 alarm_cycle [31:0] $end
$scope begin $ivl_for_loop4 $end
$var integer 32 8 i [31:0] $end
$upscope $end
$upscope $end
$scope task check $end
$upscope $end
$scope task reset_dut $end
$upscope $end
$scope task send_alternating $end
$scope begin $ivl_for_loop1 $end
$upscope $end
$upscope $end
$scope task send_bit $end
$upscope $end
$scope task send_const $end
$scope begin $ivl_for_loop0 $end
$upscope $end
$upscope $end
$scope task send_lfsr $end
$scope begin $ivl_for_loop2 $end
$upscope $end
$upscope $end
$upscope $end
$enddefinitions $end
$comment Show the parameter values. $end
$dumpall
b1010 /
b1000000000 .
b110011010 -
b1001 ,
$end
#0
$dumpvars
b0 8
b0 7
b0 6
b0 5
b0 4
13
02
01
b0 0
0+
b0 *
b0 )
0(
bx '
0&
0%
0$
0#
0"
1!
$end
#10000
1&
#20000
0&
#30000
1&
#40000
0&
#50000
1&
#60000
0&
#70000
1&
#71000
1(
#80000
0&
#90000
1&
#100000
1%
0&
#110000
03
b1 4
b1 0
1&
#111000
0%
#120000
1%
1$
0&
#130000
b10 4
1&
#131000
0%
#140000
1%
0$
0&
#150000
b11 4
b10 0
1&
#151000
0%
#160000
1%
1$
0&
#170000
b100 4
1&
#171000
0%
#180000
1%
0$
0&
#190000
b101 4
b11 0
1&
#191000
0%
#200000
1%
1$
0&
#210000
b110 4
1&
#211000
0%
#220000
1%
0$
0&
#230000
b111 4
b100 0
1&
#231000
0%
#240000
1%
1$
0&
#250000
b1000 4
1&
#251000
0%
#260000
1%
0$
0&
#270000
b1001 4
b101 0
1&
#271000
0%
#280000
1%
1$
0&
#290000
b1010 4
1&
#291000
0%
#300000
1%
0$
0&
#310000
b1011 4
b110 0
1&
#311000
0%
#320000
1%
1$
0&
#330000
b1100 4
1&
#331000
0%
#340000
1%
0$
0&
#350000
b1101 4
b111 0
1&
#351000
0%
#360000
1%
1$
0&
#370000
b1110 4
1&
#371000
0%
#380000
1%
0$
0&
#390000
b1111 4
b1000 0
1&
#391000
0%
#400000
1%
1$
0&
#410000
b10000 4
1&
#411000
0%
#420000
1%
0$
0&
#430000
b10001 4
b1001 0
1&
#431000
0%
#440000
1%
1$
0&
#450000
b10010 4
1&
#451000
0%
#460000
1%
0$
0&
#470000
b10011 4
b1010 0
1&
#471000
0%
#480000
1%
1$
0&
#490000
b10100 4
1&
#491000
0%
#500000
1%
0$
0&
#510000
b10101 4
b1011 0
1&
#511000
0%
#520000
1%
1$
0&
#530000
b10110 4
1&
#531000
0%
#540000
1%
0$
0&
#550000
b10111 4
b1100 0
1&
#551000
0%
#560000
1%
1$
0&
#570000
b11000 4
1&
#571000
0%
#580000
1%
0$
0&
#590000
b11001 4
b1101 0
1&
#591000
0%
#600000
1%
1$
0&
#610000
b11010 4
1&
#611000
0%
#620000
1%
0$
0&
#630000
b11011 4
b1110 0
1&
#631000
0%
#640000
1%
1$
0&
#650000
b11100 4
1&
#651000
0%
#660000
1%
0$
0&
#670000
b11101 4
b1111 0
1&
#671000
0%
#680000
1%
1$
0&
#690000
b11110 4
1&
#691000
0%
#700000
1%
0$
0&
#710000
b11111 4
b10000 0
1&
#711000
0%
#720000
1%
1$
0&
#730000
b100000 4
1&
#731000
0%
#740000
1%
0$
0&
#750000
b100001 4
b10001 0
1&
#751000
0%
#760000
1%
1$
0&
#770000
b100010 4
1&
#771000
0%
#780000
1%
0$
0&
#790000
b100011 4
b10010 0
1&
#791000
0%
#800000
1%
1$
0&
#810000
b100100 4
1&
#811000
0%
#820000
1%
0$
0&
#830000
b100101 4
b10011 0
1&
#831000
0%
#840000
1%
1$
0&
#850000
b100110 4
1&
#851000
0%
#860000
1%
0$
0&
#870000
b100111 4
b10100 0
1&
#871000
0%
#880000
1%
1$
0&
#890000
b101000 4
1&
#891000
0%
#900000
1%
0$
0&
#910000
b101001 4
b10101 0
1&
#911000
0%
#920000
1%
1$
0&
#930000
b101010 4
1&
#931000
0%
#940000
1%
0$
0&
#950000
b101011 4
b10110 0
1&
#951000
0%
#960000
1%
1$
0&
#970000
b101100 4
1&
#971000
0%
#980000
1%
0$
0&
#990000
b101101 4
b10111 0
1&
#991000
0%
#1000000
1%
1$
0&
#1010000
b101110 4
1&
#1011000
0%
#1020000
1%
0$
0&
#1030000
b101111 4
b11000 0
1&
#1031000
0%
#1040000
1%
1$
0&
#1050000
b110000 4
1&
#1051000
0%
#1060000
1%
0$
0&
#1070000
b110001 4
b11001 0
1&
#1071000
0%
#1080000
1%
1$
0&
#1090000
b110010 4
1&
#1091000
0%
#1100000
1%
0$
0&
#1110000
b110011 4
b11010 0
1&
#1111000
0%
#1120000
1%
1$
0&
#1130000
b110100 4
1&
#1131000
0%
#1140000
1%
0$
0&
#1150000
b110101 4
b11011 0
1&
#1151000
0%
#1160000
1%
1$
0&
#1170000
b110110 4
1&
#1171000
0%
#1180000
1%
0$
0&
#1190000
b110111 4
b11100 0
1&
#1191000
0%
#1200000
1%
1$
0&
#1210000
b111000 4
1&
#1211000
0%
#1220000
1%
0$
0&
#1230000
b111001 4
b11101 0
1&
#1231000
0%
#1240000
1%
1$
0&
#1250000
b111010 4
1&
#1251000
0%
#1260000
1%
0$
0&
#1270000
b111011 4
b11110 0
1&
#1271000
0%
#1280000
1%
1$
0&
#1290000
b111100 4
1&
#1291000
0%
#1300000
1%
0$
0&
#1310000
b111101 4
b11111 0
1&
#1311000
0%
#1320000
1%
1$
0&
#1330000
b111110 4
1&
#1331000
0%
#1340000
1%
0$
0&
#1350000
b111111 4
b100000 0
1&
#1351000
0%
#1360000
1%
1$
0&
#1370000
b1000000 4
1&
#1371000
0%
#1380000
1%
0$
0&
#1390000
b1000001 4
b100001 0
1&
#1391000
0%
#1400000
1%
1$
0&
#1410000
b1000010 4
1&
#1411000
0%
#1420000
1%
0$
0&
#1430000
b1000011 4
b100010 0
1&
#1431000
0%
#1440000
1%
1$
0&
#1450000
b1000100 4
1&
#1451000
0%
#1460000
1%
0$
0&
#1470000
b1000101 4
b100011 0
1&
#1471000
0%
#1480000
1%
1$
0&
#1490000
b1000110 4
1&
#1491000
0%
#1500000
1%
0$
0&
#1510000
b1000111 4
b100100 0
1&
#1511000
0%
#1520000
1%
1$
0&
#1530000
b1001000 4
1&
#1531000
0%
#1540000
1%
0$
0&
#1550000
b1001001 4
b100101 0
1&
#1551000
0%
#1560000
1%
1$
0&
#1570000
b1001010 4
1&
#1571000
0%
#1580000
1%
0$
0&
#1590000
b1001011 4
b100110 0
1&
#1591000
0%
#1600000
1%
1$
0&
#1610000
b1001100 4
1&
#1611000
0%
#1620000
1%
0$
0&
#1630000
b1001101 4
b100111 0
1&
#1631000
0%
#1640000
1%
1$
0&
#1650000
b1001110 4
1&
#1651000
0%
#1660000
1%
0$
0&
#1670000
b1001111 4
b101000 0
1&
#1671000
0%
#1680000
1%
1$
0&
#1690000
b1010000 4
1&
#1691000
0%
#1700000
1%
0$
0&
#1710000
b1010001 4
b101001 0
1&
#1711000
0%
#1720000
1%
1$
0&
#1730000
b1010010 4
1&
#1731000
0%
#1740000
1%
0$
0&
#1750000
b1010011 4
b101010 0
1&
#1751000
0%
#1760000
1%
1$
0&
#1770000
b1010100 4
1&
#1771000
0%
#1780000
1%
0$
0&
#1790000
b1010101 4
b101011 0
1&
#1791000
0%
#1800000
1%
1$
0&
#1810000
b1010110 4
1&
#1811000
0%
#1820000
1%
0$
0&
#1830000
b1010111 4
b101100 0
1&
#1831000
0%
#1840000
1%
1$
0&
#1850000
b1011000 4
1&
#1851000
0%
#1860000
1%
0$
0&
#1870000
b1011001 4
b101101 0
1&
#1871000
0%
#1880000
1%
1$
0&
#1890000
b1011010 4
1&
#1891000
0%
#1900000
1%
0$
0&
#1910000
b1011011 4
b101110 0
1&
#1911000
0%
#1920000
1%
1$
0&
#1930000
b1011100 4
1&
#1931000
0%
#1940000
1%
0$
0&
#1950000
b1011101 4
b101111 0
1&
#1951000
0%
#1960000
1%
1$
0&
#1970000
b1011110 4
1&
#1971000
0%
#1980000
1%
0$
0&
#1990000
b1011111 4
b110000 0
1&
#1991000
0%
#2000000
1%
1$
0&
#2010000
b1100000 4
1&
#2011000
0%
#2020000
1%
0$
0&
#2030000
b1100001 4
b110001 0
1&
#2031000
0%
#2040000
1%
1$
0&
#2050000
b1100010 4
1&
#2051000
0%
#2060000
1%
0$
0&
#2070000
b1100011 4
b110010 0
1&
#2071000
0%
#2080000
1%
1$
0&
#2090000
b1100100 4
1&
#2091000
0%
#2100000
1%
0$
0&
#2110000
b1100101 4
b110011 0
1&
#2111000
0%
#2120000
1%
1$
0&
#2130000
b1100110 4
1&
#2131000
0%
#2140000
1%
0$
0&
#2150000
b1100111 4
b110100 0
1&
#2151000
0%
#2160000
1%
1$
0&
#2170000
b1101000 4
1&
#2171000
0%
#2180000
1%
0$
0&
#2190000
b1101001 4
b110101 0
1&
#2191000
0%
#2200000
1%
1$
0&
#2210000
b1101010 4
1&
#2211000
0%
#2220000
1%
0$
0&
#2230000
b1101011 4
b110110 0
1&
#2231000
0%
#2240000
1%
1$
0&
#2250000
b1101100 4
1&
#2251000
0%
#2260000
1%
0$
0&
#2270000
b1101101 4
b110111 0
1&
#2271000
0%
#2280000
1%
1$
0&
#2290000
b1101110 4
1&
#2291000
0%
#2300000
1%
0$
0&
#2310000
b1101111 4
b111000 0
1&
#2311000
0%
#2320000
1%
1$
0&
#2330000
b1110000 4
1&
#2331000
0%
#2340000
1%
0$
0&
#2350000
b1110001 4
b111001 0
1&
#2351000
0%
#2360000
1%
1$
0&
#2370000
b1110010 4
1&
#2371000
0%
#2380000
1%
0$
0&
#2390000
b1110011 4
b111010 0
1&
#2391000
0%
#2400000
1%
1$
0&
#2410000
b1110100 4
1&
#2411000
0%
#2420000
1%
0$
0&
#2430000
b1110101 4
b111011 0
1&
#2431000
0%
#2440000
1%
1$
0&
#2450000
b1110110 4
1&
#2451000
0%
#2460000
1%
0$
0&
#2470000
b1110111 4
b111100 0
1&
#2471000
0%
#2480000
1%
1$
0&
#2490000
b1111000 4
1&
#2491000
0%
#2500000
1%
0$
0&
#2510000
b1111001 4
b111101 0
1&
#2511000
0%
#2520000
1%
1$
0&
#2530000
b1111010 4
1&
#2531000
0%
#2540000
1%
0$
0&
#2550000
b1111011 4
b111110 0
1&
#2551000
0%
#2560000
1%
1$
0&
#2570000
b1111100 4
1&
#2571000
0%
#2580000
1%
0$
0&
#2590000
b1111101 4
b111111 0
1&
#2591000
0%
#2600000
1%
1$
0&
#2610000
b1111110 4
1&
#2611000
0%
#2620000
1%
0$
0&
#2630000
b1111111 4
b1000000 0
1&
#2631000
0%
#2640000
1%
1$
0&
#2650000
b10000000 4
1&
#2651000
0%
#2660000
1%
0$
0&
#2670000
b10000001 4
b1000001 0
1&
#2671000
0%
#2680000
1%
1$
0&
#2690000
b10000010 4
1&
#2691000
0%
#2700000
1%
0$
0&
#2710000
b10000011 4
b1000010 0
1&
#2711000
0%
#2720000
1%
1$
0&
#2730000
b10000100 4
1&
#2731000
0%
#2740000
1%
0$
0&
#2750000
b10000101 4
b1000011 0
1&
#2751000
0%
#2760000
1%
1$
0&
#2770000
b10000110 4
1&
#2771000
0%
#2780000
1%
0$
0&
#2790000
b10000111 4
b1000100 0
1&
#2791000
0%
#2800000
1%
1$
0&
#2810000
b10001000 4
1&
#2811000
0%
#2820000
1%
0$
0&
#2830000
b10001001 4
b1000101 0
1&
#2831000
0%
#2840000
1%
1$
0&
#2850000
b10001010 4
1&
#2851000
0%
#2860000
1%
0$
0&
#2870000
b10001011 4
b1000110 0
1&
#2871000
0%
#2880000
1%
1$
0&
#2890000
b10001100 4
1&
#2891000
0%
#2900000
1%
0$
0&
#2910000
b10001101 4
b1000111 0
1&
#2911000
0%
#2920000
1%
1$
0&
#2930000
b10001110 4
1&
#2931000
0%
#2940000
1%
0$
0&
#2950000
b10001111 4
b1001000 0
1&
#2951000
0%
#2960000
1%
1$
0&
#2970000
b10010000 4
1&
#2971000
0%
#2980000
1%
0$
0&
#2990000
b10010001 4
b1001001 0
1&
#2991000
0%
#3000000
1%
1$
0&
#3010000
b10010010 4
1&
#3011000
0%
#3020000
1%
0$
0&
#3030000
b10010011 4
b1001010 0
1&
#3031000
0%
#3040000
1%
1$
0&
#3050000
b10010100 4
1&
#3051000
0%
#3060000
1%
0$
0&
#3070000
b10010101 4
b1001011 0
1&
#3071000
0%
#3080000
1%
1$
0&
#3090000
b10010110 4
1&
#3091000
0%
#3100000
1%
0$
0&
#3110000
b10010111 4
b1001100 0
1&
#3111000
0%
#3120000
1%
1$
0&
#3130000
b10011000 4
1&
#3131000
0%
#3140000
1%
0$
0&
#3150000
b10011001 4
b1001101 0
1&
#3151000
0%
#3160000
1%
1$
0&
#3170000
b10011010 4
1&
#3171000
0%
#3180000
1%
0$
0&
#3190000
b10011011 4
b1001110 0
1&
#3191000
0%
#3200000
1%
1$
0&
#3210000
b10011100 4
1&
#3211000
0%
#3220000
1%
0$
0&
#3230000
b10011101 4
b1001111 0
1&
#3231000
0%
#3240000
1%
1$
0&
#3250000
b10011110 4
1&
#3251000
0%
#3260000
1%
0$
0&
#3270000
b10011111 4
b1010000 0
1&
#3271000
0%
#3280000
1%
1$
0&
#3290000
b10100000 4
1&
#3291000
0%
#3300000
1%
0$
0&
#3310000
b10100001 4
b1010001 0
1&
#3311000
0%
#3320000
1%
1$
0&
#3330000
b10100010 4
1&
#3331000
0%
#3340000
1%
0$
0&
#3350000
b10100011 4
b1010010 0
1&
#3351000
0%
#3360000
1%
1$
0&
#3370000
b10100100 4
1&
#3371000
0%
#3380000
1%
0$
0&
#3390000
b10100101 4
b1010011 0
1&
#3391000
0%
#3400000
1%
1$
0&
#3410000
b10100110 4
1&
#3411000
0%
#3420000
1%
0$
0&
#3430000
b10100111 4
b1010100 0
1&
#3431000
0%
#3440000
1%
1$
0&
#3450000
b10101000 4
1&
#3451000
0%
#3460000
1%
0$
0&
#3470000
b10101001 4
b1010101 0
1&
#3471000
0%
#3480000
1%
1$
0&
#3490000
b10101010 4
1&
#3491000
0%
#3500000
1%
0$
0&
#3510000
b10101011 4
b1010110 0
1&
#3511000
0%
#3520000
1%
1$
0&
#3530000
b10101100 4
1&
#3531000
0%
#3540000
1%
0$
0&
#3550000
b10101101 4
b1010111 0
1&
#3551000
0%
#3560000
1%
1$
0&
#3570000
b10101110 4
1&
#3571000
0%
#3580000
1%
0$
0&
#3590000
b10101111 4
b1011000 0
1&
#3591000
0%
#3600000
1%
1$
0&
#3610000
b10110000 4
1&
#3611000
0%
#3620000
1%
0$
0&
#3630000
b10110001 4
b1011001 0
1&
#3631000
0%
#3640000
1%
1$
0&
#3650000
b10110010 4
1&
#3651000
0%
#3660000
1%
0$
0&
#3670000
b10110011 4
b1011010 0
1&
#3671000
0%
#3680000
1%
1$
0&
#3690000
b10110100 4
1&
#3691000
0%
#3700000
1%
0$
0&
#3710000
b10110101 4
b1011011 0
1&
#3711000
0%
#3720000
1%
1$
0&
#3730000
b10110110 4
1&
#3731000
0%
#3740000
1%
0$
0&
#3750000
b10110111 4
b1011100 0
1&
#3751000
0%
#3760000
1%
1$
0&
#3770000
b10111000 4
1&
#3771000
0%
#3780000
1%
0$
0&
#3790000
b10111001 4
b1011101 0
1&
#3791000
0%
#3800000
1%
1$
0&
#3810000
b10111010 4
1&
#3811000
0%
#3820000
1%
0$
0&
#3830000
b10111011 4
b1011110 0
1&
#3831000
0%
#3840000
1%
1$
0&
#3850000
b10111100 4
1&
#3851000
0%
#3860000
1%
0$
0&
#3870000
b10111101 4
b1011111 0
1&
#3871000
0%
#3880000
1%
1$
0&
#3890000
b10111110 4
1&
#3891000
0%
#3900000
1%
0$
0&
#3910000
b10111111 4
b1100000 0
1&
#3911000
0%
#3920000
1%
1$
0&
#3930000
b11000000 4
1&
#3931000
0%
#3940000
1%
0$
0&
#3950000
b11000001 4
b1100001 0
1&
#3951000
0%
#3960000
1%
1$
0&
#3970000
b11000010 4
1&
#3971000
0%
#3980000
1%
0$
0&
#3990000
b11000011 4
b1100010 0
1&
#3991000
0%
#4000000
1%
1$
0&
#4010000
b11000100 4
1&
#4011000
0%
#4020000
1%
0$
0&
#4030000
b11000101 4
b1100011 0
1&
#4031000
0%
#4040000
1%
1$
0&
#4050000
b11000110 4
1&
#4051000
0%
#4060000
1%
0$
0&
#4070000
b11000111 4
b1100100 0
1&
#4071000
0%
#4080000
1%
1$
0&
#4090000
b11001000 4
1&
#4091000
0%
#4100000
1%
0$
0&
#4110000
b11001001 4
b1100101 0
1&
#4111000
0%
#4120000
1%
1$
0&
#4130000
b11001010 4
1&
#4131000
0%
#4140000
1%
0$
0&
#4150000
b11001011 4
b1100110 0
1&
#4151000
0%
#4160000
1%
1$
0&
#4170000
b11001100 4
1&
#4171000
0%
#4180000
1%
0$
0&
#4190000
b11001101 4
b1100111 0
1&
#4191000
0%
#4200000
1%
1$
0&
#4210000
b11001110 4
1&
#4211000
0%
#4220000
1%
0$
0&
#4230000
b11001111 4
b1101000 0
1&
#4231000
0%
#4240000
1%
1$
0&
#4250000
b11010000 4
1&
#4251000
0%
#4260000
1%
0$
0&
#4270000
b11010001 4
b1101001 0
1&
#4271000
0%
#4280000
1%
1$
0&
#4290000
b11010010 4
1&
#4291000
0%
#4300000
1%
0$
0&
#4310000
b11010011 4
b1101010 0
1&
#4311000
0%
#4320000
1%
1$
0&
#4330000
b11010100 4
1&
#4331000
0%
#4340000
1%
0$
0&
#4350000
b11010101 4
b1101011 0
1&
#4351000
0%
#4360000
1%
1$
0&
#4370000
b11010110 4
1&
#4371000
0%
#4380000
1%
0$
0&
#4390000
b11010111 4
b1101100 0
1&
#4391000
0%
#4400000
1%
1$
0&
#4410000
b11011000 4
1&
#4411000
0%
#4420000
1%
0$
0&
#4430000
b11011001 4
b1101101 0
1&
#4431000
0%
#4440000
1%
1$
0&
#4450000
b11011010 4
1&
#4451000
0%
#4460000
1%
0$
0&
#4470000
b11011011 4
b1101110 0
1&
#4471000
0%
#4480000
1%
1$
0&
#4490000
b11011100 4
1&
#4491000
0%
#4500000
1%
0$
0&
#4510000
b11011101 4
b1101111 0
1&
#4511000
0%
#4520000
1%
1$
0&
#4530000
b11011110 4
1&
#4531000
0%
#4540000
1%
0$
0&
#4550000
b11011111 4
b1110000 0
1&
#4551000
0%
#4560000
1%
1$
0&
#4570000
b11100000 4
1&
#4571000
0%
#4580000
1%
0$
0&
#4590000
b11100001 4
b1110001 0
1&
#4591000
0%
#4600000
1%
1$
0&
#4610000
b11100010 4
1&
#4611000
0%
#4620000
1%
0$
0&
#4630000
b11100011 4
b1110010 0
1&
#4631000
0%
#4640000
1%
1$
0&
#4650000
b11100100 4
1&
#4651000
0%
#4660000
1%
0$
0&
#4670000
b11100101 4
b1110011 0
1&
#4671000
0%
#4680000
1%
1$
0&
#4690000
b11100110 4
1&
#4691000
0%
#4700000
1%
0$
0&
#4710000
b11100111 4
b1110100 0
1&
#4711000
0%
#4720000
1%
1$
0&
#4730000
b11101000 4
1&
#4731000
0%
#4740000
1%
0$
0&
#4750000
b11101001 4
b1110101 0
1&
#4751000
0%
#4760000
1%
1$
0&
#4770000
b11101010 4
1&
#4771000
0%
#4780000
1%
0$
0&
#4790000
b11101011 4
b1110110 0
1&
#4791000
0%
#4800000
1%
1$
0&
#4810000
b11101100 4
1&
#4811000
0%
#4820000
1%
0$
0&
#4830000
b11101101 4
b1110111 0
1&
#4831000
0%
#4840000
1%
1$
0&
#4850000
b11101110 4
1&
#4851000
0%
#4860000
1%
0$
0&
#4870000
b11101111 4
b1111000 0
1&
#4871000
0%
#4880000
1%
1$
0&
#4890000
b11110000 4
1&
#4891000
0%
#4900000
1%
0$
0&
#4910000
b11110001 4
b1111001 0
1&
#4911000
0%
#4920000
1%
1$
0&
#4930000
b11110010 4
1&
#4931000
0%
#4940000
1%
0$
0&
#4950000
b11110011 4
b1111010 0
1&
#4951000
0%
#4960000
1%
1$
0&
#4970000
b11110100 4
1&
#4971000
0%
#4980000
1%
0$
0&
#4990000
b11110101 4
b1111011 0
1&
#4991000
0%
#5000000
1%
1$
0&
#5010000
b11110110 4
1&
#5011000
0%
#5020000
1%
0$
0&
#5030000
b11110111 4
b1111100 0
1&
#5031000
0%
#5040000
1%
1$
0&
#5050000
b11111000 4
1&
#5051000
0%
#5060000
1%
0$
0&
#5070000
b11111001 4
b1111101 0
1&
#5071000
0%
#5080000
1%
1$
0&
#5090000
b11111010 4
1&
#5091000
0%
#5100000
1%
0$
0&
#5110000
b11111011 4
b1111110 0
1&
#5111000
0%
#5120000
1%
1$
0&
#5130000
b11111100 4
1&
#5131000
0%
#5140000
1%
0$
0&
#5150000
b11111101 4
b1111111 0
1&
#5151000
0%
#5160000
1%
1$
0&
#5170000
b11111110 4
1&
#5171000
0%
#5180000
1%
0$
0&
#5190000
b11111111 4
b10000000 0
1&
#5191000
0%
